[
  {
    "rank": 1,
    "id": "cmiydzmww000p8qoj70tjo3xc",
    "score": 2.122494615025763,
    "percentile": 100,
    "wins": 29,
    "losses": 0,
    "totalComparisons": 29,
    "winRate": 100,
    "url": "https://pub-348e171b4d40413abdb8c2b075b6de0d.r2.dev/samples/1765255215302-0222b43b-fed4-4fad-b540-f029625da829.jpg",
    "gender": "female",
    "estimatedAge": 23
  },
  {
    "rank": 2,
    "id": "cmiydzmww000t8qoj2eyx8b29",
    "score": 2.118021540237852,
    "percentile": 98,
    "wins": 35,
    "losses": 4,
    "totalComparisons": 39,
    "winRate": 89.7,
    "url": "https://pub-348e171b4d40413abdb8c2b075b6de0d.r2.dev/samples/1765255215306-c7c0dc20-ec40-496f-9969-def38da99ed8.jpg",
    "gender": "female",
    "estimatedAge": 26
  },
  {
    "rank": 3,
    "id": "cmiydzmww00118qojuz2qwxqi",
    "score": 2.001820155661021,
    "percentile": 96,
    "wins": 28,
    "losses": 2,
    "totalComparisons": 30,
    "winRate": 93.3,
    "url": "https://pub-348e171b4d40413abdb8c2b075b6de0d.r2.dev/samples/1765255217076-15b87978-3f0f-4994-853c-fbb1a0936f9a.jpg",
    "gender": "female",
    "estimatedAge": 20
  },
  {
    "rank": 4,
    "id": "cmiydzmwx00178qojkuq61yxa",
    "score": 1.965365651189385,
    "percentile": 94,
    "wins": 31,
    "losses": 3,
    "totalComparisons": 34,
    "winRate": 91.2,
    "url": "https://pub-348e171b4d40413abdb8c2b075b6de0d.r2.dev/samples/1765255218956-9645a5f7-1e87-4e7c-8812-034f5e33816b.jpg",
    "gender": "female",
    "estimatedAge": 24
  },
  {
    "rank": 5,
    "id": "cmiydzmww000n8qojl5b39yjq",
    "score": 1.961165676400939,
    "percentile": 92,
    "wins": 26,
    "losses": 1,
    "totalComparisons": 27,
    "winRate": 96.3,
    "url": "https://pub-348e171b4d40413abdb8c2b075b6de0d.r2.dev/samples/1765255215294-f565eac9-392a-495d-8f55-90014f90a2f3.jpg",
    "gender": "female",
    "estimatedAge": 20
  },
  {
    "rank": 6,
    "id": "cmiydzmww000x8qojxa1ykr1u",
    "score": 1.954232561430727,
    "percentile": 90,
    "wins": 31,
    "losses": 4,
    "totalComparisons": 35,
    "winRate": 88.6,
    "url": "https://pub-348e171b4d40413abdb8c2b075b6de0d.r2.dev/samples/1765255217065-88628a2a-aed4-4865-b3ba-e5f1ad433725.jpg",
    "gender": "female",
    "estimatedAge": 26
  },
  {
    "rank": 7,
    "id": "cmiydzmww000i8qojkaqudb7n",
    "score": 1.829863933162802,
    "percentile": 88,
    "wins": 27,
    "losses": 4,
    "totalComparisons": 31,
    "winRate": 87.1,
    "url": "https://pub-348e171b4d40413abdb8c2b075b6de0d.r2.dev/samples/1765255213513-5970bb7b-bfa6-409e-8694-186efceb8d9f.jpg",
    "gender": "female",
    "estimatedAge": 23
  },
  {
    "rank": 8,
    "id": "cmiydzmww000s8qojpkvj5x1x",
    "score": 1.750599237597798,
    "percentile": 86,
    "wins": 25,
    "losses": 6,
    "totalComparisons": 31,
    "winRate": 80.6,
    "url": "https://pub-348e171b4d40413abdb8c2b075b6de0d.r2.dev/samples/1765255215306-0bd50045-fb8f-49c9-be72-315fdec86c2c.jpg",
    "gender": "female",
    "estimatedAge": 27
  },
  {
    "rank": 9,
    "id": "cmiydzmww00088qojf4hhldps",
    "score": 1.722576023287876,
    "percentile": 84,
    "wins": 28,
    "losses": 6,
    "totalComparisons": 34,
    "winRate": 82.4,
    "url": "https://pub-348e171b4d40413abdb8c2b075b6de0d.r2.dev/samples/1765255211609-7d8ff809-27e0-40b5-99eb-4c37f4cc3504.jpg",
    "gender": "female",
    "estimatedAge": 28
  },
  {
    "rank": 10,
    "id": "cmiydzmwx001f8qojsfhficcj",
    "score": 1.684252240320376,
    "percentile": 82,
    "wins": 25,
    "losses": 6,
    "totalComparisons": 31,
    "winRate": 80.6,
    "url": "https://pub-348e171b4d40413abdb8c2b075b6de0d.r2.dev/samples/1765255221014-cde0304c-27f3-4d20-b26c-e611a71b72c3.jpg",
    "gender": "female",
    "estimatedAge": 20
  },
  {
    "rank": 11,
    "id": "cmiydzmww000z8qojeapeo06c",
    "score": 1.498156349116209,
    "percentile": 80,
    "wins": 20,
    "losses": 6,
    "totalComparisons": 26,
    "winRate": 76.9,
    "url": "https://pub-348e171b4d40413abdb8c2b075b6de0d.r2.dev/samples/1765255217073-8724625f-b186-44a8-a0c0-501d2475d8a2.jpg",
    "gender": "female",
    "estimatedAge": 19
  },
  {
    "rank": 12,
    "id": "cmiydzmwx00138qojiyn5noi5",
    "score": 1.48129024552307,
    "percentile": 78,
    "wins": 24,
    "losses": 10,
    "totalComparisons": 34,
    "winRate": 70.6,
    "url": "https://pub-348e171b4d40413abdb8c2b075b6de0d.r2.dev/samples/1765255217077-6054232e-d203-45c2-a75d-b5286ab00d7b.jpg",
    "gender": "female",
    "estimatedAge": 27
  },
  {
    "rank": 13,
    "id": "cmiydzmww000y8qoj4fus61yw",
    "score": 1.479231949750329,
    "percentile": 76,
    "wins": 26,
    "losses": 9,
    "totalComparisons": 35,
    "winRate": 74.3,
    "url": "https://pub-348e171b4d40413abdb8c2b075b6de0d.r2.dev/samples/1765255217072-97894789-a765-4ced-8b42-bc9a7fb7b139.jpg",
    "gender": "female",
    "estimatedAge": 24
  },
  {
    "rank": 14,
    "id": "cmiydzmww000v8qoj5qwij620",
    "score": 1.469692179959897,
    "percentile": 74,
    "wins": 25,
    "losses": 10,
    "totalComparisons": 35,
    "winRate": 71.4,
    "url": "https://pub-348e171b4d40413abdb8c2b075b6de0d.r2.dev/samples/1765255217063-34670b60-95b7-4b86-b3cd-e40b3e888d35.jpg",
    "gender": "female",
    "estimatedAge": 25
  },
  {
    "rank": 15,
    "id": "cmiydzmwx001i8qojygqqpsj8",
    "score": 1.467129725001259,
    "percentile": 72,
    "wins": 22,
    "losses": 8,
    "totalComparisons": 30,
    "winRate": 73.3,
    "url": "https://pub-348e171b4d40413abdb8c2b075b6de0d.r2.dev/samples/1765255221027-4449eef1-94c3-482f-9828-bac184d29bf5.jpg",
    "gender": "female",
    "estimatedAge": 19
  },
  {
    "rank": 16,
    "id": "cmiydzmww000q8qojqsw989ws",
    "score": 1.407102475170121,
    "percentile": 70,
    "wins": 17,
    "losses": 7,
    "totalComparisons": 24,
    "winRate": 70.8,
    "url": "https://pub-348e171b4d40413abdb8c2b075b6de0d.r2.dev/samples/1765255215304-cd8ebc06-9636-4b5e-a124-0ec7acb62a63.jpg",
    "gender": "female",
    "estimatedAge": 26
  },
  {
    "rank": 17,
    "id": "cmiydzmwx001c8qojwdlyohkp",
    "score": 1.357273252188201,
    "percentile": 68,
    "wins": 21,
    "losses": 9,
    "totalComparisons": 30,
    "winRate": 70,
    "url": "https://pub-348e171b4d40413abdb8c2b075b6de0d.r2.dev/samples/1765255218962-8fdce1c9-facd-4001-80c4-86ddba3c4c87.jpg",
    "gender": "female",
    "estimatedAge": 21
  },
  {
    "rank": 18,
    "id": "cmiydzmww000a8qojpmh9xniv",
    "score": 1.33856796636676,
    "percentile": 66,
    "wins": 21,
    "losses": 9,
    "totalComparisons": 30,
    "winRate": 70,
    "url": "https://pub-348e171b4d40413abdb8c2b075b6de0d.r2.dev/samples/1765255213494-4fff4f20-0a6c-45ee-b6c9-aa0fb8276281.jpg",
    "gender": "female",
    "estimatedAge": 26
  },
  {
    "rank": 19,
    "id": "cmiydzmww000h8qoj43xea7d5",
    "score": 1.284546659066759,
    "percentile": 64,
    "wins": 20,
    "losses": 10,
    "totalComparisons": 30,
    "winRate": 66.7,
    "url": "https://pub-348e171b4d40413abdb8c2b075b6de0d.r2.dev/samples/1765255213512-2d85d4d4-91d4-4aa6-9eba-49c9d43bf648.jpg",
    "gender": "female",
    "estimatedAge": 27
  },
  {
    "rank": 20,
    "id": "cmiydzmww000b8qojm46asppd",
    "score": 1.213498054049622,
    "percentile": 62,
    "wins": 19,
    "losses": 12,
    "totalComparisons": 31,
    "winRate": 61.3,
    "url": "https://pub-348e171b4d40413abdb8c2b075b6de0d.r2.dev/samples/1765255213495-e8f15674-7664-43c7-89a5-2a6ff5ed3a63.jpg",
    "gender": "female",
    "estimatedAge": 28
  },
  {
    "rank": 21,
    "id": "cmiydzmww00098qojkl0yus4c",
    "score": 1.19123071488274,
    "percentile": 60,
    "wins": 20,
    "losses": 13,
    "totalComparisons": 33,
    "winRate": 60.6,
    "url": "https://pub-348e171b4d40413abdb8c2b075b6de0d.r2.dev/samples/1765255211611-9cf35c9e-47d9-478b-8e90-913c0b939a28.jpg",
    "gender": "female",
    "estimatedAge": 20
  },
  {
    "rank": 22,
    "id": "cmiydzmww000j8qojcich3akr",
    "score": 1.013658497745424,
    "percentile": 58,
    "wins": 15,
    "losses": 13,
    "totalComparisons": 28,
    "winRate": 53.6,
    "url": "https://pub-348e171b4d40413abdb8c2b075b6de0d.r2.dev/samples/1765255213514-4cbeb02e-4a44-4a12-b331-473afec072fb.jpg",
    "gender": "female",
    "estimatedAge": 29
  },
  {
    "rank": 23,
    "id": "cmiydzmww00028qojvn6ymx3d",
    "score": 1.004207228749781,
    "percentile": 56,
    "wins": 10,
    "losses": 10,
    "totalComparisons": 20,
    "winRate": 50,
    "url": "https://pub-348e171b4d40413abdb8c2b075b6de0d.r2.dev/samples/1765255211569-d73a4e91-37ca-4d49-ab95-63f0d37b0636.jpg",
    "gender": "female",
    "estimatedAge": 29
  },
  {
    "rank": 24,
    "id": "cmiydzmww00058qoj87yzi845",
    "score": 0.980371201281796,
    "percentile": 54,
    "wins": 11,
    "losses": 11,
    "totalComparisons": 22,
    "winRate": 50,
    "url": "https://pub-348e171b4d40413abdb8c2b075b6de0d.r2.dev/samples/1765255211606-dd2af346-7761-4b24-a0b4-07d4484f32fb.jpg",
    "gender": "female",
    "estimatedAge": 26
  },
  {
    "rank": 25,
    "id": "cmiydzmwx001l8qojefu965p2",
    "score": 0.9469163076626477,
    "percentile": 52,
    "wins": 15,
    "losses": 16,
    "totalComparisons": 31,
    "winRate": 48.4,
    "url": "https://pub-348e171b4d40413abdb8c2b075b6de0d.r2.dev/samples/1765255221033-1672f7cb-fe69-4841-a3b7-c954db8e9584.jpg",
    "gender": "female",
    "estimatedAge": 29
  },
  {
    "rank": 26,
    "id": "cmiydzmww000o8qojfe1y8qaj",
    "score": 0.9431525426974617,
    "percentile": 50,
    "wins": 16,
    "losses": 16,
    "totalComparisons": 32,
    "winRate": 50,
    "url": "https://pub-348e171b4d40413abdb8c2b075b6de0d.r2.dev/samples/1765255215301-02758407-8abf-4a0d-967b-048b1d6bd374.jpg",
    "gender": "female",
    "estimatedAge": 23
  },
  {
    "rank": 27,
    "id": "cmiydzmww000m8qoj3nvj5jrj",
    "score": 0.889508115397759,
    "percentile": 48,
    "wins": 14,
    "losses": 17,
    "totalComparisons": 31,
    "winRate": 45.2,
    "url": "https://pub-348e171b4d40413abdb8c2b075b6de0d.r2.dev/samples/1765255215290-ac2d7037-97f8-4452-8aca-934d7320b397.jpg",
    "gender": "female",
    "estimatedAge": 23
  },
  {
    "rank": 28,
    "id": "cmiydzmwx001a8qojujwk096l",
    "score": 0.8890027138017782,
    "percentile": 46,
    "wins": 15,
    "losses": 18,
    "totalComparisons": 33,
    "winRate": 45.5,
    "url": "https://pub-348e171b4d40413abdb8c2b075b6de0d.r2.dev/samples/1765255218960-5ff4a73a-2f3d-4d59-b12c-f59d0a686e46.jpg",
    "gender": "female",
    "estimatedAge": 25
  },
  {
    "rank": 29,
    "id": "cmiydzmww00068qojgiksbsdo",
    "score": 0.6634901211992494,
    "percentile": 44,
    "wins": 11,
    "losses": 24,
    "totalComparisons": 35,
    "winRate": 31.4,
    "url": "https://pub-348e171b4d40413abdb8c2b075b6de0d.r2.dev/samples/1765255211607-e21481e5-edf5-4364-a181-3bd1502f5687.jpg",
    "gender": "female",
    "estimatedAge": 20
  },
  {
    "rank": 30,
    "id": "cmiydzmww000d8qojuzbie6zj",
    "score": 0.6201689657179724,
    "percentile": 42,
    "wins": 11,
    "losses": 21,
    "totalComparisons": 32,
    "winRate": 34.4,
    "url": "https://pub-348e171b4d40413abdb8c2b075b6de0d.r2.dev/samples/1765255213504-43393008-e23b-4c45-93b3-ea0ff2da9424.jpg",
    "gender": "female",
    "estimatedAge": 27
  },
  {
    "rank": 31,
    "id": "cmiydzmww000l8qojcapryjy2",
    "score": 0.5676110218033136,
    "percentile": 40,
    "wins": 11,
    "losses": 22,
    "totalComparisons": 33,
    "winRate": 33.3,
    "url": "https://pub-348e171b4d40413abdb8c2b075b6de0d.r2.dev/samples/1765255215287-12e471bc-24b4-42c8-a75c-9a7d9179fd76.jpg",
    "gender": "female",
    "estimatedAge": 18
  },
  {
    "rank": 32,
    "id": "cmiydzmwx001e8qojytaf7e6b",
    "score": 0.5611204710056148,
    "percentile": 38,
    "wins": 8,
    "losses": 19,
    "totalComparisons": 27,
    "winRate": 29.6,
    "url": "https://pub-348e171b4d40413abdb8c2b075b6de0d.r2.dev/samples/1765255221007-47fe0e6c-04d4-4446-8e5e-b6b9446e7098.jpg",
    "gender": "female",
    "estimatedAge": 24
  },
  {
    "rank": 33,
    "id": "cmiydzmwx001k8qoj8jwr51zv",
    "score": 0.5456620402498955,
    "percentile": 36,
    "wins": 7,
    "losses": 18,
    "totalComparisons": 25,
    "winRate": 28,
    "url": "https://pub-348e171b4d40413abdb8c2b075b6de0d.r2.dev/samples/1765255221032-4c3a202b-1b94-4f8a-a15c-1ac7be218518.jpg",
    "gender": "female",
    "estimatedAge": 23
  },
  {
    "rank": 34,
    "id": "cmiydzmwx001h8qoj5aixuru9",
    "score": 0.5398960215885948,
    "percentile": 34,
    "wins": 11,
    "losses": 23,
    "totalComparisons": 34,
    "winRate": 32.4,
    "url": "https://pub-348e171b4d40413abdb8c2b075b6de0d.r2.dev/samples/1765255221022-03693c52-cccf-48c5-b722-9654580ed6f4.jpg",
    "gender": "female",
    "estimatedAge": 29
  },
  {
    "rank": 35,
    "id": "cmiydzmww00038qojytzsru2p",
    "score": 0.5256866930155211,
    "percentile": 32,
    "wins": 8,
    "losses": 23,
    "totalComparisons": 31,
    "winRate": 25.8,
    "url": "https://pub-348e171b4d40413abdb8c2b075b6de0d.r2.dev/samples/1765255211572-9e4a1bc4-e960-48a9-8000-f694306a34e1.jpg",
    "gender": "female",
    "estimatedAge": 21
  },
  {
    "rank": 36,
    "id": "cmiydzmwx001d8qojszf923m1",
    "score": 0.5062918508026311,
    "percentile": 30,
    "wins": 11,
    "losses": 21,
    "totalComparisons": 32,
    "winRate": 34.4,
    "url": "https://pub-348e171b4d40413abdb8c2b075b6de0d.r2.dev/samples/1765255218962-e59f0c9f-b0ca-4bfe-b874-5c8e04becf44.jpg",
    "gender": "female",
    "estimatedAge": 18
  },
  {
    "rank": 37,
    "id": "cmiydzmww00078qojmxkqhqwc",
    "score": 0.5042850085456525,
    "percentile": 28,
    "wins": 9,
    "losses": 26,
    "totalComparisons": 35,
    "winRate": 25.7,
    "url": "https://pub-348e171b4d40413abdb8c2b075b6de0d.r2.dev/samples/1765255211608-254f2d70-f0a8-41d6-ba4a-6303a648336c.jpg",
    "gender": "female",
    "estimatedAge": 29
  },
  {
    "rank": 38,
    "id": "cmiydzmwx001b8qoj2v69fnjl",
    "score": 0.4925763152597285,
    "percentile": 26,
    "wins": 9,
    "losses": 21,
    "totalComparisons": 30,
    "winRate": 30,
    "url": "https://pub-348e171b4d40413abdb8c2b075b6de0d.r2.dev/samples/1765255218961-61808496-d883-4736-a980-3330d1fe1f71.jpg",
    "gender": "female",
    "estimatedAge": 29
  },
  {
    "rank": 39,
    "id": "cmiydzmww000k8qoj0ghi3nqk",
    "score": 0.415065655040687,
    "percentile": 24,
    "wins": 5,
    "losses": 23,
    "totalComparisons": 28,
    "winRate": 17.9,
    "url": "https://pub-348e171b4d40413abdb8c2b075b6de0d.r2.dev/samples/1765255215286-3f740605-4a0b-4be3-a7f5-31276fa8610f.jpg",
    "gender": "female",
    "estimatedAge": 22
  },
  {
    "rank": 40,
    "id": "cmiydzmww00008qojufl5adfu",
    "score": 0.4097543760427714,
    "percentile": 22,
    "wins": 6,
    "losses": 22,
    "totalComparisons": 28,
    "winRate": 21.4,
    "url": "https://pub-348e171b4d40413abdb8c2b075b6de0d.r2.dev/samples/1765255211564-d0dbe6fa-a815-49c9-bc01-8dc9bdbefcfe.jpg",
    "gender": "female",
    "estimatedAge": 25
  },
  {
    "rank": 41,
    "id": "cmiydzmww000r8qoj1z12jz4j",
    "score": 0.4025874333302628,
    "percentile": 20,
    "wins": 7,
    "losses": 25,
    "totalComparisons": 32,
    "winRate": 21.9,
    "url": "https://pub-348e171b4d40413abdb8c2b075b6de0d.r2.dev/samples/1765255215305-6b03d5d6-a147-44ad-8986-9046fae0822b.jpg",
    "gender": "female",
    "estimatedAge": 18
  },
  {
    "rank": 42,
    "id": "cmiydzmww000f8qoj7s57o1dv",
    "score": 0.3779574499333559,
    "percentile": 18,
    "wins": 5,
    "losses": 24,
    "totalComparisons": 29,
    "winRate": 17.2,
    "url": "https://pub-348e171b4d40413abdb8c2b075b6de0d.r2.dev/samples/1765255213510-81532add-6016-416f-a018-5e93c0311a79.jpg",
    "gender": "female",
    "estimatedAge": 24
  },
  {
    "rank": 43,
    "id": "cmiydzmwx00168qoj5q3dcbuc",
    "score": 0.3530915511883223,
    "percentile": 16,
    "wins": 6,
    "losses": 23,
    "totalComparisons": 29,
    "winRate": 20.7,
    "url": "https://pub-348e171b4d40413abdb8c2b075b6de0d.r2.dev/samples/1765255218947-6ca161aa-d217-453c-992a-8aab4061b0e8.jpg",
    "gender": "female",
    "estimatedAge": 26
  },
  {
    "rank": 44,
    "id": "cmiydzmwx00148qojvliwrfac",
    "score": 0.3221799261562535,
    "percentile": 14,
    "wins": 3,
    "losses": 24,
    "totalComparisons": 27,
    "winRate": 11.1,
    "url": "https://pub-348e171b4d40413abdb8c2b075b6de0d.r2.dev/samples/1765255218938-4aee9665-d2fd-415a-ac90-4eb5e892ab1f.jpg",
    "gender": "female",
    "estimatedAge": 25
  },
  {
    "rank": 45,
    "id": "cmiydzmwx00198qoj6ygx6dcp",
    "score": 0.3078863997942492,
    "percentile": 12,
    "wins": 4,
    "losses": 23,
    "totalComparisons": 27,
    "winRate": 14.8,
    "url": "https://pub-348e171b4d40413abdb8c2b075b6de0d.r2.dev/samples/1765255218958-7f665ef1-deee-4c05-9b38-fa36cc00c2b7.jpg",
    "gender": "female",
    "estimatedAge": 28
  },
  {
    "rank": 46,
    "id": "cmiydzmww00108qoj0r7448kw",
    "score": 0.2983402097271102,
    "percentile": 10,
    "wins": 5,
    "losses": 24,
    "totalComparisons": 29,
    "winRate": 17.2,
    "url": "https://pub-348e171b4d40413abdb8c2b075b6de0d.r2.dev/samples/1765255217074-7a03698a-7850-40b2-9e93-0fc1cab3093b.jpg",
    "gender": "female",
    "estimatedAge": 19
  },
  {
    "rank": 47,
    "id": "cmiydzmww000w8qoje7hj9ghl",
    "score": 0.279932357426442,
    "percentile": 8,
    "wins": 4,
    "losses": 29,
    "totalComparisons": 33,
    "winRate": 12.1,
    "url": "https://pub-348e171b4d40413abdb8c2b075b6de0d.r2.dev/samples/1765255217065-02ec9fdd-d621-4cb8-875f-beb1497f4034.jpg",
    "gender": "female",
    "estimatedAge": 29
  },
  {
    "rank": 48,
    "id": "cmiydzmww000u8qojlekzyaqb",
    "score": 0.1163437039551615,
    "percentile": 6,
    "wins": 0,
    "losses": 28,
    "totalComparisons": 28,
    "winRate": 0,
    "url": "https://pub-348e171b4d40413abdb8c2b075b6de0d.r2.dev/samples/1765255217057-28ccb818-ebb1-400e-919b-839255e52c8c.jpg",
    "gender": "female",
    "estimatedAge": 18
  },
  {
    "rank": 49,
    "id": "cmiydzmww000g8qojvbqju663",
    "score": 0.1154310172271979,
    "percentile": 4,
    "wins": 3,
    "losses": 30,
    "totalComparisons": 33,
    "winRate": 9.1,
    "url": "https://pub-348e171b4d40413abdb8c2b075b6de0d.r2.dev/samples/1765255213511-5f25ae0f-4e5b-4122-b12a-821f058d5bc2.jpg",
    "gender": "female",
    "estimatedAge": 20
  },
  {
    "rank": 50,
    "id": "cmiydzmwx00128qoj6fpuhnl7",
    "score": 0.1097135982638585,
    "percentile": 2,
    "wins": 1,
    "losses": 28,
    "totalComparisons": 29,
    "winRate": 3.4,
    "url": "https://pub-348e171b4d40413abdb8c2b075b6de0d.r2.dev/samples/1765255217076-4d787967-eef5-4998-be70-e2b105ce970f.jpg",
    "gender": "female",
    "estimatedAge": 23
  }
]